tp_http_request_response_parser/__init__.py
tp_http_request_response_parser-2025.9.30.dist-info/LICENSE
tp_http_request_response_parser-2025.9.30.dist-info/METADATA
tp_http_request_response_parser-2025.9.30.dist-info/WHEEL
tp_http_request_response_parser-2025.9.30.dist-info/top_level.txt
tp_http_request_response_parser-2025.9.30.dist-info/RECORD
