Metadata-Version: 2.1
Name: tp-http-request-response-parser
Version: 2025.9.30
Summary: Parse/ Unparse the HTTP Request/ Response
Author-email: TP Cyber Security <tpcybersec2023@gmail.com>
License: MIT
Project-URL: Homepage, https://github.com/TPCyberSec/TP-HTTP-Request-Response-Parser
Keywords: TPCyberSec,HTTP Request Parser,HTTP Response Parser
Classifier: Programming Language :: Python :: 3
Classifier: Programming Language :: Python :: Implementation :: Jython
License-File: LICENSE
Requires-Dist: json-duplicate-keys>=2025.9.30
